{"cameraMode":{"drawMode":0,"name":"Shaded","section":"Shading Mode"},"sceneLighting":false,"audioPlay":false,"sceneViewState":{"m_AlwaysRefresh":false,"showFog":true,"showSkybox":false,"showFlares":true,"showImageEffects":true,"showParticleSystems":true,"showVisualEffectGraphs":true,"m_FxEnabled":true},"in2DMode":false,"pivot":{"x":-12.746173858642579,"y":-2.8396852016448976,"z":9.650888442993164},"rotation":{"x":0.10450062900781632,"y":-0.6858646273612976,"z":0.10050448775291443,"w":0.7131474018096924},"size":9.351287841796875,"orthographic":false}